{
  "recipe_index": {
    "aliases": {
      "recipe_index_write": {}
    },
    "mappings": {},
    "settings": {
      "index": {
        "creation_date": "1541441417847",
        "analysis": {
          "filter": {
            "russian_stemmer": {
              "type": "stemmer",
              "language": "russian"
            },
            "russian_stop": {
              "type": "stop",
              "stopwords": "_russian_"
            }
          },
          "analyzer": {
            "russian": {
              "filter": [
                "lowercase",
                "russian_stop",
                "russian_stemmer"
              ],
              "tokenizer": "standard"
            }
          }
        },
        "number_of_shards": "5",
        "number_of_replicas": "1",
        "uuid": "LpmRnjtxTQyqv0wK60vkXQ",
        "version": {
          "created": "2030199"
        }
      }
    },
    "warmers": {}
  }
}